txtoflow/__init__.py
txtoflow/txtoflow.py
txtoflow-0.3.2.data/scripts/txtoflow
txtoflow-0.3.2.dist-info/LICENSE
txtoflow-0.3.2.dist-info/METADATA
txtoflow-0.3.2.dist-info/WHEEL
txtoflow-0.3.2.dist-info/top_level.txt
txtoflow-0.3.2.dist-info/RECORD
