Metadata-Version: 2.1
Name: txtoflow
Version: 0.3.2
Summary: Library to generate flowcharts from pseudo code
Home-page: https://krishkasula.gitlab.io/txtoflow/index.html
Author: Krishna
Author-email: krishna.vijay4444@gmail.com
License: MIT License
Keywords: automatic flowchart,code2flow,text2flow,text to flowchart,txtoflow
Platform: any
Classifier: Programming Language :: Python :: 3
Classifier: License :: OSI Approved :: MIT License
Classifier: Operating System :: OS Independent
Requires-Dist: pygraphviz
Requires-Dist: sly
